slack_mcp/__init__.py
slack_mcp/blockkit.py
slack_mcp/client.py
slack_mcp/server.py
barie_slack_mcp-0.1.1.dist-info/METADATA
barie_slack_mcp-0.1.1.dist-info/WHEEL
barie_slack_mcp-0.1.1.dist-info/entry_points.txt
barie_slack_mcp-0.1.1.dist-info/RECORD
